predectorutils/__init__.py
predectorutils/baseconv.py
predectorutils/checksum.py
predectorutils/database.py
predectorutils/exceptions.py
predectorutils/gff.py
predectorutils/higher.py
predectorutils/main.py
predectorutils/parsers.py
predectorutils/regex.py
predectorutils/analyses/__init__.py
predectorutils/analyses/apoplastp.py
predectorutils/analyses/base.py
predectorutils/analyses/deeploc.py
predectorutils/analyses/deepredeff.py
predectorutils/analyses/deepsig.py
predectorutils/analyses/deeptmhmm.py
predectorutils/analyses/effectorp.py
predectorutils/analyses/hhr.py
predectorutils/analyses/hmmer.py
predectorutils/analyses/localizer.py
predectorutils/analyses/mmseqs.py
predectorutils/analyses/pepstats.py
predectorutils/analyses/pfamscan.py
predectorutils/analyses/phobius.py
predectorutils/analyses/regex.py
predectorutils/analyses/signalp.py
predectorutils/analyses/targetp.py
predectorutils/analyses/tmhmm.py
predectorutils/data/__init__.py
predectorutils/data/hmms_of_interest.json
predectorutils/data/learn_to_rank-config.json
predectorutils/data/learn_to_rank-features.json
predectorutils/data/learn_to_rank-model.json
predectorutils/subcommands/__init__.py
predectorutils/subcommands/analysis_tables.py
predectorutils/subcommands/decode.py
predectorutils/subcommands/dump_db.py
predectorutils/subcommands/encode.py
predectorutils/subcommands/getorf_to_gff.py
predectorutils/subcommands/gff.py
predectorutils/subcommands/ipr_to_gff.py
predectorutils/subcommands/load_db.py
predectorutils/subcommands/map_to_genome.py
predectorutils/subcommands/precomputed.py
predectorutils/subcommands/prot_to_genome.py
predectorutils/subcommands/r2js.py
predectorutils/subcommands/rank.py
predectorutils/subcommands/regex.py
predectorutils/subcommands/scores_to_genome.py
predectorutils/subcommands/split_fasta.py
predectorutils-0.9.1.dist-info/LICENSE
predectorutils-0.9.1.dist-info/METADATA
predectorutils-0.9.1.dist-info/WHEEL
predectorutils-0.9.1.dist-info/entry_points.txt
predectorutils-0.9.1.dist-info/top_level.txt
predectorutils-0.9.1.dist-info/RECORD
