Metadata-Version: 2.1
Name: predectorutils
Version: 0.9.1
Summary: Utility scripts for the predector pipeline.
Home-page: https://github.com/ccdmb/predector
Author: Darcy Jones
Author-email: darcy.a.jones@postgrad.curtin.edu.au
License: Apache 2.0
Keywords: fungi machine-learning bioinformatics
Classifier: Development Status :: 4 - Beta
Classifier: License :: OSI Approved :: Apache Software License
Classifier: Programming Language :: Python :: 3
Classifier: Programming Language :: Python :: 3.7
Classifier: Programming Language :: Python :: 3.8
License-File: LICENSE
Requires-Dist: biopython (>=1.70)
Requires-Dist: pandas
Requires-Dist: numpy
Requires-Dist: xgboost
Requires-Dist: intervaltree
Provides-Extra: dev
Requires-Dist: check-manifest ; extra == 'dev'
Requires-Dist: scipy ; extra == 'dev'
Requires-Dist: scikit-learn ; extra == 'dev'
Requires-Dist: jupyter ; extra == 'dev'
Requires-Dist: matplotlib ; extra == 'dev'
Requires-Dist: seaborn ; extra == 'dev'
Requires-Dist: pandas ; extra == 'dev'
Provides-Extra: test
Requires-Dist: coverage ; extra == 'test'
Requires-Dist: pytest ; extra == 'test'
Requires-Dist: mypy ; extra == 'test'
Requires-Dist: types-setuptools ; extra == 'test'
